mcpserver_zyq/__init__.py
mcpserver_zyq/weathertest.py
mcpserver_zyq-0.1.0.dist-info/METADATA
mcpserver_zyq-0.1.0.dist-info/WHEEL
mcpserver_zyq-0.1.0.dist-info/entry_points.txt
mcpserver_zyq-0.1.0.dist-info/RECORD
