Metadata-Version: 2.4
Name: mcpserver-zyq
Version: 0.1.0
Summary: Add your description here
Author-email: 雨晴 <zhuyuqingzhuyuqing@alibaba-inc.com>
Requires-Python: >=3.10
Requires-Dist: mcp[cli]>=1.7.1
